llegom/__init__.py
llegom-0.1.0.dist-info/METADATA
llegom-0.1.0.dist-info/WHEEL
llegom-0.1.0.dist-info/RECORD
