Metadata-Version: 2.1
Name: llegom
Version: 0.1.0
Summary: Modular library for building LLM powered applications
Author: Aditya Gudimella
Author-email: aditya.gudimella@gmail.com
Requires-Python: >=3.10,<4.0
Classifier: Programming Language :: Python :: 3
Classifier: Programming Language :: Python :: 3.10
Classifier: Programming Language :: Python :: 3.11
